LICENSE
MANIFEST.in
README.md
setup.py
forges/__init__.py
forges/animation.py
forges/build.py
forges/color.py
forges/entity.py
forges/error.py
forges/font_manager.py
forges/input.py
forges/intro.py
forges/main.py
forges/math.py
forges/mixer.py
forges/object.py
forges/script.py
forges/sprite.py
forges/text.py
forges/window.py
forges.egg-info/PKG-INFO
forges.egg-info/SOURCES.txt
forges.egg-info/dependency_links.txt
forges.egg-info/requires.txt
forges.egg-info/top_level.txt
forges/assets/fonts/roboto/LICENSE.txt
forges/assets/fonts/roboto/Roboto-Black.ttf
forges/assets/fonts/roboto/Roboto-BlackItalic.ttf
forges/assets/fonts/roboto/Roboto-Bold.ttf
forges/assets/fonts/roboto/Roboto-BoldItalic.ttf
forges/assets/fonts/roboto/Roboto-Italic.ttf
forges/assets/fonts/roboto/Roboto-Light.ttf
forges/assets/fonts/roboto/Roboto-LightItalic.ttf
forges/assets/fonts/roboto/Roboto-Medium.ttf
forges/assets/fonts/roboto/Roboto-MediumItalic.ttf
forges/assets/fonts/roboto/Roboto-Regular.ttf
forges/assets/fonts/roboto/Roboto-Thin.ttf
forges/assets/fonts/roboto/Roboto-ThinItalic.ttf
forges/assets/icon/icon.png
forges/assets/icon/icon_ico.ico
forges/assets/icon/icon_white.png
forges/assets/logo/logo.png
forges/prefabs/__init__.py
forges/prefabs/button.py
forges/prefabs/camera.py
forges/prefabs/checkbox.py
forges/prefabs/platformer_controller.py
forges/prefabs/top_view_controller.py
forges/scripts/__init__.py
forges/scripts/gravity.py
forges/scripts/toggle_fullscreen.py