Metadata-Version: 2.1
Name: forges
Version: 0.0.6
Summary: A game engine made with SDL 2.
Home-page: https://github.com/Aermoss/ForgeS
Author: Yusuf Rencber
Author-email: yusufrencber546@gmail.com
License: MIT
Platform: UNKNOWN
License-File: LICENSE
